{
  "type": "minecraft:chest",
  "pools": [
    {
      "bonus_rolls": 0.0,
      "entries": [
        {
          "type": "minecraft:item",
          "functions": [
            {
              "add": false,
              "count": {
                "type": "minecraft:uniform",
                "max": 7.0,
                "min": 3.0
              },
              "function": "minecraft:set_count"
            }
          ],
          "name": "minecraft:diamond"
        },
        {
          "type": "minecraft:item",
          "functions": [
            {
              "add": false,
              "count": {
                "type": "minecraft:uniform",
                "max": 10.0,
                "min": 5.0
              },
              "function": "minecraft:set_count"
            }
          ],
          "name": "minecraft:emerald"
        },
        {
          "type": "minecraft:item",
          "functions": [
            {
              "add": false,
              "count": {
                "type": "minecraft:uniform",
                "max": 16.0,
                "min": 8.0
              },
              "function": "minecraft:set_count"
            }
          ],
          "name": "minecraft:gold_ingot"
        },
        {
          "type": "minecraft:item",
          "functions": [
            {
              "add": false,
              "count": {
                "type": "minecraft:uniform",
                "max": 2.0,
                "min": 1.0
              },
              "function": "minecraft:set_count"
            }
          ],
          "name": "minecraft:gold_block"
        }
      ],
      "rolls": 3.0
    },
    {
      "bonus_rolls": 0.0,
      "conditions": [
        {
          "chance": 0.35,
          "condition": "minecraft:random_chance"
        }
      ],
      "entries": [
        {
          "type": "minecraft:item",
          "functions": [
            {
              "add": false,
              "count": {
                "type": "minecraft:uniform",
                "max": 4.0,
                "min": 2.0
              },
              "function": "minecraft:set_count"
            }
          ],
          "name": "minecraft:netherite_scrap"
        }
      ],
      "rolls": 1.0
    },
    {
      "bonus_rolls": 0.0,
      "conditions": [
        {
          "chance": 0.15,
          "condition": "minecraft:random_chance"
        }
      ],
      "entries": [
        {
          "type": "minecraft:item",
          "functions": [
            {
              "add": false,
              "count": {
                "type": "minecraft:uniform",
                "max": 1.0,
                "min": 1.0
              },
              "function": "minecraft:set_count"
            }
          ],
          "name": "minecraft:netherite_ingot"
        }
      ],
      "rolls": 1.0
    },
    {
      "bonus_rolls": 0.0,
      "conditions": [
        {
          "chance": 0.1,
          "condition": "minecraft:random_chance"
        }
      ],
      "entries": [
        {
          "type": "minecraft:item",
          "functions": [
            {
              "add": false,
              "count": {
                "type": "minecraft:uniform",
                "max": 1.0,
                "min": 1.0
              },
              "function": "minecraft:set_count"
            }
          ],
          "name": "void-dimension:void_shard"
        }
      ],
      "rolls": 1.0
    }
  ]
}